bonsai_gym_common/__init__.py
bonsai_gym_common/bonsai_logging.py
bonsai_gym_common/gym_simulator.py
bonsai_gym_common/image_gym_simulator.py
bonsai_gym_common/test_gym_simulator.py
bonsai_gym_common-0.7.4.dist-info/DESCRIPTION.rst
bonsai_gym_common-0.7.4.dist-info/METADATA
bonsai_gym_common-0.7.4.dist-info/RECORD
bonsai_gym_common-0.7.4.dist-info/WHEEL
bonsai_gym_common-0.7.4.dist-info/metadata.json
bonsai_gym_common-0.7.4.dist-info/top_level.txt
