Metadata-Version: 2.0
Name: bonsai-gym-common
Version: 0.7.4
Summary: A library to integrate Bonsai BRAIN with OpenAI Gym environments
Home-page: http://github.com/BonsaiAI/bonsai-gym-common
Author: Bonsai Engineering
Author-email: opensource@bons.ai
License: BSD
Keywords: bonsai
Platform: UNKNOWN
Classifier: Development Status :: 4 - Beta
Classifier: Intended Audience :: Developers
Classifier: Topic :: Scientific/Engineering :: Artificial Intelligence
Classifier: License :: OSI Approved :: BSD License
Classifier: Programming Language :: Python :: 2
Classifier: Programming Language :: Python :: 2.7
Classifier: Programming Language :: Python :: 3
Classifier: Programming Language :: Python :: 3.4
Classifier: Programming Language :: Python :: 3.5
Classifier: Natural Language :: English
Requires-Dist: bonsai-python (>=0.12.0)
Requires-Dist: gym (<=0.7.3,>=0.7.0)
